deltakit_core/__init__.py
deltakit_core/deprecation.py
deltakit_core/py.typed
deltakit_core/data_formats/__init__.py
deltakit_core/data_formats/_b801_parsers.py
deltakit_core/data_formats/_measurements.py
deltakit_core/decoding_graphs/__init__.py
deltakit_core/decoding_graphs/_data_qubits.py
deltakit_core/decoding_graphs/_decoding_graph.py
deltakit_core/decoding_graphs/_decoding_graph_tools.py
deltakit_core/decoding_graphs/_dem_parsing.py
deltakit_core/decoding_graphs/_explained_dem_parsing.py
deltakit_core/decoding_graphs/_hypergraph_annotations_tools.py
deltakit_core/decoding_graphs/_hypergraph_decomposition.py
deltakit_core/decoding_graphs/_syndromes.py
deltakit_core/decoding_graphs/_weighted_graphs.py
deltakit_core/decoding_graphs/_windowing_utils.py
deltakit_core/plotting/colours.py
deltakit_core-0.6.2.dist-info/licenses/LICENSE
deltakit_core-0.6.2.dist-info/METADATA
deltakit_core-0.6.2.dist-info/WHEEL
deltakit_core-0.6.2.dist-info/top_level.txt
deltakit_core-0.6.2.dist-info/RECORD
